element_recognition/__init__.py
element_recognition/_test.py
element_recognition/element_recognition.py
element_recognition-1.1.4.dist-info/LICENSE
element_recognition-1.1.4.dist-info/METADATA
element_recognition-1.1.4.dist-info/WHEEL
element_recognition-1.1.4.dist-info/top_level.txt
element_recognition-1.1.4.dist-info/RECORD
