Metadata-Version: 2.1
Name: element-recognition
Version: 1.1.4
Summary: You can get element ratio.
Home-page: http://github.com/yu9824/element_recognition/
Author: yu9824
Author-email: yu.9824.job@gmail.com
Maintainer: yu9824
Maintainer-email: yu.9824.job@gmail.com
License: MIT
Platform: UNKNOWN
Classifier: License :: OSI Approved :: MIT License
Classifier: Programming Language :: Python :: 3
Classifier: Programming Language :: Python :: 3.6
Classifier: Programming Language :: Python :: 3.7
Classifier: Programming Language :: Python :: 3.8
Classifier: Programming Language :: Python :: 3.9
License-File: LICENSE
Requires-Dist: numpy
Requires-Dist: pandas
